{
  "track": {
    "name": "Dreamflasher",
    "mbid": "4780b6a9-1ccf-4149-bd62-ec84663f8eec",
    "url": "https://www.last.fm/music/Jane+Remover/_/Dreamflasher",
    "duration": "224000",
    "streamable": {
      "#text": "0",
      "fulltrack": "0"
    },
    "listeners": "140470",
    "playcount": "1777149",
    "artist": {
      "name": "Jane Remover",
      "mbid": "f4b6e451-5dce-4842-a555-f793892299b3",
      "url": "https://www.last.fm/music/Jane+Remover"
    },
    "album": {
      "artist": "Jane Remover",
      "title": "Revengeseekerz",
      "url": "https://www.last.fm/music/Jane+Remover/Revengeseekerz",
      "image": [
        {
          "#text": "https://lastfm.freetls.fastly.net/i/u/34s/7e63ec5a92240a2f3292aa15bd5af39a.png",
          "size": "small"
        },
        {
          "#text": "https://lastfm.freetls.fastly.net/i/u/64s/7e63ec5a92240a2f3292aa15bd5af39a.png",
          "size": "medium"
        },
        {
          "#text": "https://lastfm.freetls.fastly.net/i/u/174s/7e63ec5a92240a2f3292aa15bd5af39a.png",
          "size": "large"
        },
        {
          "#text": "https://lastfm.freetls.fastly.net/i/u/300x300/7e63ec5a92240a2f3292aa15bd5af39a.png",
          "size": "extralarge"
        }
      ]
    },
    "toptags": {
      "tag": [
        {
          "name": "rage",
          "url": "https://www.last.fm/tag/rage"
        },
        {
          "name": "digicore",
          "url": "https://www.last.fm/tag/digicore"
        },
        {
          "name": "electronic",
          "url": "https://www.last.fm/tag/electronic"
        },
        {
          "name": "hip hop",
          "url": "https://www.last.fm/tag/hip+hop"
        },
        {
          "name": "glitch pop",
          "url": "https://www.last.fm/tag/glitch+pop"
        }
      ]
    }
  }
}