{
  "track": {
    "name": "No Sleep",
    "mbid": "001673aa-bc4e-44c5-a1d5-9ccb9ea69e23",
    "url": "https://www.last.fm/music/nettspend/_/No+Sleep",
    "duration": "132000",
    "streamable": {
      "#text": "0",
      "fulltrack": "0"
    },
    "listeners": "50398",
    "playcount": "374571",
    "artist": {
      "name": "nettspend",
      "url": "https://www.last.fm/music/nettspend"
    },
    "album": {
      "artist": "nettspend",
      "title": "Early Life Crisis",
      "url": "https://www.last.fm/music/nettspend/Early+Life+Crisis",
      "image": [
        {
          "#text": "https://lastfm.freetls.fastly.net/i/u/34s/c8aa095fb407e2869048fbd7d8152e92.png",
          "size": "small"
        },
        {
          "#text": "https://lastfm.freetls.fastly.net/i/u/64s/c8aa095fb407e2869048fbd7d8152e92.png",
          "size": "medium"
        },
        {
          "#text": "https://lastfm.freetls.fastly.net/i/u/174s/c8aa095fb407e2869048fbd7d8152e92.png",
          "size": "large"
        },
        {
          "#text": "https://lastfm.freetls.fastly.net/i/u/300x300/c8aa095fb407e2869048fbd7d8152e92.png",
          "size": "extralarge"
        }
      ]
    },
    "toptags": {
      "tag": []
    },
    "wiki": {
      "published": "12 Mar 2026, 13:27",
      "summary": "“no sleep” is the twelfth track to Nettspend’s debut studio album, early life crisis. It showcases Nettspend going back to his original roots, rapping over a Jerk beat for the first time in a long time. The Jerk instrumental was produced by frequent collaborator cranes and consists of bit-crushed synths, smooth bass and fast-paced percussion. On December 26, 2025, the track would be previewed twice by Nettspend on an Instagram live. On February 12 <a href=\"http://www.last.fm/music/nettspend/_/No+Sleep\">Read more on Last.fm</a>.",
      "content": "“no sleep” is the twelfth track to Nettspend’s debut studio album, early life crisis. It showcases Nettspend going back to his original roots, rapping over a Jerk beat for the first time in a long time. The Jerk instrumental was produced by frequent collaborator cranes and consists of bit-crushed synths, smooth bass and fast-paced percussion. On December 26, 2025, the track would be previewed twice by Nettspend on an Instagram live. On February 12, 2026, the track would be played in its entirety on an Australian radio station during an interview leading up to the release of early life crisis. Nettspend released “no sleep” on March 6, 2026. “no sleep” by Nettspend was produced by cranes. <a href=\"http://www.last.fm/music/nettspend/_/No+Sleep\">Read more on Last.fm</a>. User-contributed text is available under the Creative Commons By-SA License; additional terms may apply."
    }
  }
}